[{"id":"530901","name":"市辖区"},{"id":"530902","name":"临翔区"},{"id":"530921","name":"凤庆县"},{"id":"530922","name":"云县"},{"id":"530923","name":"永德县"},{"id":"530924","name":"镇康县"},{"id":"530925","name":"双江拉祜族佤族布朗族傣族自治县"},{"id":"530926","name":"耿马傣族佤族自治县"},{"id":"530927","name":"沧源佤族自治县"},{"id":"530902001","name":"凤翔街道办事处"},{"id":"530902002","name":"忙畔街道办事处"},{"id":"530902102","name":"博尚镇"},{"id":"530902202","name":"南美乡"},{"id":"530902203","name":"蚂蚁堆乡"},{"id":"530902204","name":"章驮乡"},{"id":"530902206","name":"圈内乡"},{"id":"530902207","name":"马台乡"},{"id":"530902208","name":"邦东乡"},{"id":"530902209","name":"平村乡"},{"id":"530921101","name":"凤山镇"},{"id":"530921102","name":"鲁史镇"},{"id":"530921103","name":"小湾镇"},{"id":"530921104","name":"营盘镇"},{"id":"530921105","name":"三岔河镇"},{"id":"530921106","name":"勐佑镇"},{"id":"530921107","name":"雪山镇"},{"id":"530921108","name":"洛党镇"},{"id":"530921201","name":"诗礼乡"},{"id":"530921202","name":"新华乡"},{"id":"530921204","name":"大寺乡"},{"id":"530921206","name":"腰街乡"},{"id":"530921207","name":"郭大寨乡"},{"id":"530922101","name":"爱华镇"},{"id":"530922102","name":"漫湾镇"},{"id":"530922103","name":"大朝山西镇"},{"id":"530922104","name":"涌宝镇"},{"id":"530922105","name":"茂兰镇"},{"id":"530922106","name":"幸福镇"},{"id":"530922107","name":"大寨镇"},{"id":"530922201","name":"忙怀乡"},{"id":"530922202","name":"晓街乡"},{"id":"530922203","name":"茶房乡"},{"id":"530922204","name":"栗树乡"},{"id":"530922205","name":"后箐乡"},{"id":"530922501","name":"幸福农场"},{"id":"530922502","name":"新城农场"},{"id":"530923101","name":"德党镇"},{"id":"530923102","name":"小勐统镇"},{"id":"530923103","name":"永康镇"},{"id":"530923203","name":"勐板乡"},{"id":"530923204","name":"亚练乡"},{"id":"530923205","name":"乌木龙乡"},{"id":"530923206","name":"大雪山乡"},{"id":"530923207","name":"班卡乡"},{"id":"530923208","name":"崇岗乡"},{"id":"530923209","name":"大山乡"},{"id":"530923401","name":"勐底农场"},{"id":"530924101","name":"凤尾镇"},{"id":"530924102","name":"勐捧镇"},{"id":"530924103","name":"南伞镇"},{"id":"530924201","name":"忙丙乡"},{"id":"530924202","name":"勐堆乡"},{"id":"530924204","name":"木场乡"},{"id":"530924205","name":"军赛乡"},{"id":"530925101","name":"勐勐镇"},{"id":"530925102","name":"勐库镇"},{"id":"530925201","name":"沙河乡"},{"id":"530925202","name":"大文乡"},{"id":"530925203","name":"忙糯乡"},{"id":"530925205","name":"邦丙乡"},{"id":"530926100","name":"耿马镇"},{"id":"530926101","name":"勐永镇"},{"id":"530926102","name":"勐撒镇"},{"id":"530926103","name":"孟定镇"},{"id":"530926200","name":"大兴乡"},{"id":"530926201","name":"芒洪乡"},{"id":"530926202","name":"四排山乡"},{"id":"530926203","name":"贺派乡"},{"id":"530926204","name":"勐简乡"},{"id":"530926401","name":"耿马华侨农场"},{"id":"530926402","name":"勐撒农场"},{"id":"530926403","name":"孟定农场"},{"id":"530927101","name":"勐董镇"},{"id":"530927102","name":"岩帅镇"},{"id":"530927103","name":"勐省镇"},{"id":"530927104","name":"芒卡镇"},{"id":"530927202","name":"单甲乡"},{"id":"530927203","name":"糯良乡"},{"id":"530927204","name":"勐来乡"},{"id":"530927205","name":"勐角乡"},{"id":"530927206","name":"班洪乡"},{"id":"530927207","name":"班老乡"},{"id":"530927401","name":"勐省农场"},{"id":"530902001001","name":"章嘎社区"},{"id":"530902001002","name":"忙角社区"},{"id":"530902001003","name":"南屏社区"},{"id":"530902001004","name":"菜园社区"},{"id":"530902001005","name":"圈掌社区"},{"id":"530902001006","name":"中平社区"},{"id":"530902001007","name":"塘平社区"},{"id":"530902001008","name":"文华社区居民委员会"},{"id":"530902001009","name":"南信桥社区居民委员会"},{"id":"530902001201","name":"大石房村委会"},{"id":"530902001202","name":"老五村村委会"},{"id":"530902001203","name":"新村村委会"},{"id":"530902001204","name":"昔本村委会"},{"id":"530902001205","name":"南本村委会"},{"id":"530902001206","name":"竹篷村委会"},{"id":"530902001207","name":"南信村委会"},{"id":"530902001210","name":"中山村委会"},{"id":"530902002001","name":"忙畔社区"},{"id":"530902002002","name":"忙令社区"},{"id":"530902002003","name":"青华社区居民委员会"},{"id":"530902002203","name":"文伟村委会"},{"id":"530902002204","name":"丙简村委会"},{"id":"530902002205","name":"岔河村委会"},{"id":"530902002206","name":"明子村委会"},{"id":"530902102201","name":"博尚村委会"},{"id":"530902102202","name":"户有村委会"},{"id":"530902102203","name":"完贤村委会"},{"id":"530902102204","name":"完海村委会"},{"id":"530902102205","name":"勐托村委会"},{"id":"530902102206","name":"碗窑村委会"},{"id":"530902102207","name":"幕布村委会"},{"id":"530902102208","name":"勐准村委会"},{"id":"530902102209","name":"弯子村委会"},{"id":"530902102210","name":"永和村委会"},{"id":"530902102211","name":"永泉村委会"},{"id":"530902102212","name":"夹山村委会"},{"id":"530902102213","name":"那戈村委会"},{"id":"530902102214","name":"小那么村委会"},{"id":"530902102215","name":"大那么村委会"},{"id":"530902102216","name":"那招村委会"},{"id":"530902102217","name":"邦别村委会"},{"id":"530902102218","name":"帮公村委会"},{"id":"530902102219","name":"坝密河村委会"},{"id":"530902202201","name":"南美村委会"},{"id":"530902202202","name":"多依村委会"},{"id":"530902202203","name":"南华村委会"},{"id":"530902202204","name":"坡脚村委会"},{"id":"530902203201","name":"蚂蚁堆村委会"},{"id":"530902203202","name":"一水村委会"},{"id":"530902203203","name":"马峰腰村委会"},{"id":"530902203204","name":"邦海村委会"},{"id":"530902203205","name":"曼毫村委会"},{"id":"530902203206","name":"新民村委会"},{"id":"530902203207","name":"小河边村委会"},{"id":"530902203208","name":"曼启村委会"},{"id":"530902203209","name":"杏勒村委会"},{"id":"530902203210","name":"忙糯村委会"},{"id":"530902203211","name":"邦谷村委会"},{"id":"530902203212","name":"白河村委会"},{"id":"530902203213","name":"遮奈村委会"},{"id":"530902203214","name":"糯恩村委会"},{"id":"530902204201","name":"章驮村委会"},{"id":"530902204202","name":"邦福村委会"},{"id":"530902204203","name":"户远村委会"},{"id":"530902204204","name":"龙平村委会"},{"id":"530902204205","name":"塘房村委会"},{"id":"530902204206","name":"勐旺村委会"},{"id":"530902204207","name":"采花坝村委会"},{"id":"530902204208","name":"邦卖村委会"},{"id":"530902204209","name":"新寨村委会"},{"id":"530902206201","name":"圈内村委会"},{"id":"530902206202","name":"坝胡村委会"},{"id":"530902206203","name":"斗阁村委会"},{"id":"530902206204","name":"细博村委会"},{"id":"530902206205","name":"昆赛村委会"},{"id":"530902206206","name":"宁安村委会"},{"id":"530902206207","name":"文宁村委会"},{"id":"530902206208","name":"文远村委会"},{"id":"530902206209","name":"南赛河村委会"},{"id":"530902206210","name":"昔木村委会"},{"id":"530902206211","name":"炭窑村委会"},{"id":"530902207201","name":"马台村委会"},{"id":"530902207202","name":"清河村委会"},{"id":"530902207203","name":"琅琊村委会"},{"id":"530902207204","name":"唐家寨村委会"},{"id":"530902207205","name":"全河村委会"},{"id":"530902207206","name":"那杏村委会"},{"id":"530902207207","name":"平河村委会"},{"id":"530902207208","name":"南糯村委会"},{"id":"530902207209","name":"平掌村委会"},{"id":"530902208201","name":"邦包村委会"},{"id":"530902208202","name":"璋珍村委会"},{"id":"530902208203","name":"团山村委会"},{"id":"530902208204","name":"和平村委会"},{"id":"530902208205","name":"卫平村委会"},{"id":"530902208206","name":"邦东村委会"},{"id":"530902208207","name":"曼岗村委会"},{"id":"530902209201","name":"平村村委会"},{"id":"530902209202","name":"忙丫村委会"},{"id":"530902209203","name":"永平村委会"},{"id":"530902209204","name":"换良村委会"},{"id":"530902209205","name":"那玉村委会"},{"id":"530921101001","name":"龙泉社区"},{"id":"530921101002","name":"凤山社区"},{"id":"530921101003","name":"文明社区"},{"id":"530921101004","name":"东城社区"},{"id":"530921101201","name":"水箐村委会"},{"id":"530921101202","name":"安石村委会"},{"id":"530921101203","name":"董扁村委会"},{"id":"530921101204","name":"青树村委会"},{"id":"530921101205","name":"落星村委会"},{"id":"530921101206","name":"上寨村委会"},{"id":"530921101207","name":"东山村委会"},{"id":"530921101208","name":"麦地村委会"},{"id":"530921101209","name":"后山村委会"},{"id":"530921101210","name":"红塘村委会"},{"id":"530921101211","name":"象塘村委会"},{"id":"530921101212","name":"前锋村委会"},{"id":"530921101213","name":"大有村委会"},{"id":"530921101214","name":"等上村委会"},{"id":"530921101215","name":"京竹林村委会"},{"id":"530921101216","name":"金平村委会"},{"id":"530921101217","name":"平村村委会"},{"id":"530921101218","name":"清水河村委会"},{"id":"530921102201","name":"鲁史村委会"},{"id":"530921102202","name":"宝华村委会"},{"id":"530921102203","name":"鲁家山村委会"},{"id":"530921102204","name":"沿河村委会"},{"id":"530921102205","name":"金马村委会"},{"id":"530921102206","name":"古平村委会"},{"id":"530921102207","name":"金鸡村委会"},{"id":"530921102208","name":"凤凰村委会"},{"id":"530921102209","name":"犀牛村委会"},{"id":"530921102210","name":"力马柯村委会"},{"id":"530921102211","name":"永新村委会"},{"id":"530921102212","name":"河边村委会"},{"id":"530921102213","name":"团结村委会"},{"id":"530921102214","name":"永发村委会"},{"id":"530921102215","name":"羊头山村委会"},{"id":"530921102216","name":"老道箐村委会"},{"id":"530921102217","name":"新塘村委会"},{"id":"530921103201","name":"小湾村委会"},{"id":"530921103202","name":"蕨菜村委会"},{"id":"530921103203","name":"箐中村委会"},{"id":"530921103204","name":"正义村委会"},{"id":"530921103205","name":"温泉村委会"},{"id":"530921103206","name":"桂花村委会"},{"id":"530921103207","name":"锦秀村委会"},{"id":"530921103208","name":"华峰村委会"},{"id":"530921103209","name":"三水村委会"},{"id":"530921103210","name":"梅竹村委会"},{"id":"530921103211","name":"春光村委会"},{"id":"530921103212","name":"马街村委会"},{"id":"530921104201","name":"营盘村委会"},{"id":"530921104202","name":"大乃坝村委会"},{"id":"530921104203","name":"景杏村委会"},{"id":"530921104204","name":"贺费村委会"},{"id":"530921104205","name":"勐统村委会"},{"id":"530921104206","name":"杨家寨村委会"},{"id":"530921104207","name":"忙岗村委会"},{"id":"530921104208","name":"红立村委会"},{"id":"530921104209","name":"三塔村委会"},{"id":"530921104210","name":"邦拐村委会"},{"id":"530921104211","name":"秀塘村委会"},{"id":"530921104212","name":"忙邦村委会"},{"id":"530921104213","name":"干塘村委会"},{"id":"530921104214","name":"里拐村委会"},{"id":"530921104215","name":"安平村委会"},{"id":"530921104216","name":"田坝口村委会"},{"id":"530921104217","name":"京立安村委会"},{"id":"530921105201","name":"雪华村委会"},{"id":"530921105202","name":"光华村委会"},{"id":"530921105203","name":"松花村委会"},{"id":"530921105204","name":"涌金村委会"},{"id":"530921105205","name":"康明村委会"},{"id":"530921105206","name":"水田村委会"},{"id":"530921105207","name":"明龙村委会"},{"id":"530921105208","name":"王平村委会"},{"id":"530921105209","name":"棉花林村委会"},{"id":"530921105210","name":"秀衣庄村委会"},{"id":"530921105211","name":"山头田村委会"},{"id":"530921105212","name":"柏木村委会"},{"id":"530921105213","name":"大龙潭村委会"},{"id":"530921106201","name":"勐佑村委会"},{"id":"530921106202","name":"鱼塘村委会"},{"id":"530921106203","name":"新林村委会"},{"id":"530921106204","name":"习谦村委会"},{"id":"530921106205","name":"立果村委会"},{"id":"530921106206","name":"岔路村委会"},{"id":"530921106207","name":"白岩村委会"},{"id":"530921106208","name":"翁乐村委会"},{"id":"530921106209","name":"高山村委会"},{"id":"530921106210","name":"棕园村委会"},{"id":"530921106211","name":"安街村委会"},{"id":"530921106212","name":"河东村委会"},{"id":"530921106213","name":"中和村委会"},{"id":"530921106214","name":"新寨村委会"},{"id":"530921106215","name":"新田村委会"},{"id":"530921106216","name":"阿里侯村委会"},{"id":"530921106217","name":"大寨子村委会"},{"id":"530921106218","name":"界牌村委会"},{"id":"530921106219","name":"立达村委会"},{"id":"530921106220","name":"立平村委会"},{"id":"530921107201","name":"兴街村委会"},{"id":"530921107202","name":"中山村委会"},{"id":"530921107203","name":"立马村委会"},{"id":"530921107204","name":"荒田村委会"},{"id":"530921107205","name":"王家寨村委会"},{"id":"530921107206","name":"安和村委会"},{"id":"530921107207","name":"新民村委会"},{"id":"530921107208","name":"新化村委会"},{"id":"530921107209","name":"新联村委会"},{"id":"530921107210","name":"新文村委会"},{"id":"530921107211","name":"永顺村委会"},{"id":"530921107212","name":"新平村委会"},{"id":"530921107213","name":"桂林村委会"},{"id":"530921108201","name":"洛党村委会"},{"id":"530921108202","name":"白云村委会"},{"id":"530921108203","name":"鹿鸣村委会"},{"id":"530921108204","name":"岳舞村委会"},{"id":"530921108205","name":"礼乐村委会"},{"id":"530921108206","name":"和德村委会"},{"id":"530921108207","name":"厚丰村委会"},{"id":"530921108208","name":"水菜林村委会"},{"id":"530921108209","name":"永和村委会"},{"id":"530921108210","name":"桃花村委会"},{"id":"530921108211","name":"荣上村委会"},{"id":"530921108212","name":"田心村委会"},{"id":"530921108213","name":"太平寺村委会"},{"id":"530921108214","name":"鼎新村委会"},{"id":"530921108215","name":"箐头村委会"},{"id":"530921108216","name":"琼岳村委会"},{"id":"530921108217","name":"大兴村委会"},{"id":"530921108218","name":"新峰村委会"},{"id":"530921108219","name":"中村村委会"},{"id":"530921108220","name":"万峰村委会"},{"id":"530921201201","name":"诗礼村委会"},{"id":"530921201202","name":"永复村委会"},{"id":"530921201203","name":"孔兴村委会"},{"id":"530921201204","name":"清华村委会"},{"id":"530921201205","name":"古墨村委会"},{"id":"530921201206","name":"牌坊村委会"},{"id":"530921201207","name":"三合村委会"},{"id":"530921201208","name":"河平村委会"},{"id":"530921201209","name":"乐平村委会"},{"id":"530921201210","name":"永乐村委会"},{"id":"530921201211","name":"朝阳村委会"},{"id":"530921201212","name":"武伟村委会"},{"id":"530921201213","name":"安义村委会"},{"id":"530921201214","name":"禄丰村委会"},{"id":"530921202201","name":"新华村委会"},{"id":"530921202202","name":"白腊村委会"},{"id":"530921202203","name":"西密村委会"},{"id":"530921202204","name":"瓦屋村委会"},{"id":"530921202205","name":"沙帽村委会"},{"id":"530921202206","name":"凤云村委会"},{"id":"530921202207","name":"水源村委会"},{"id":"530921202208","name":"砚田村委会"},{"id":"530921202209","name":"紫微村委会"},{"id":"530921202210","name":"文平村委会"},{"id":"530921202211","name":"美华村委会"},{"id":"530921204201","name":"大寺村委会"},{"id":"530921204202","name":"河顺村委会"},{"id":"530921204203","name":"双龙村委会"},{"id":"530921204204","name":"回龙村委会"},{"id":"530921204205","name":"平河村委会"},{"id":"530921204206","name":"岔河村委会"},{"id":"530921204207","name":"清水村委会"},{"id":"530921204208","name":"漭街村委会"},{"id":"530921204209","name":"马庄村委会"},{"id":"530921204210","name":"德乐村委会"},{"id":"530921204211","name":"路山村委会"},{"id":"530921206201","name":"腰街村委会"},{"id":"530921206202","name":"函关村委会"},{"id":"530921206203","name":"民安村委会"},{"id":"530921206204","name":"复兴村委会"},{"id":"530921206205","name":"星源村委会"},{"id":"530921206206","name":"开明村委会"},{"id":"530921207201","name":"大立色村委会"},{"id":"530921207202","name":"琼英村委会"},{"id":"530921207203","name":"卡思村委会"},{"id":"530921207204","name":"松林村委会"},{"id":"530921207205","name":"平掌村委会"},{"id":"530921207206","name":"邦贵村委会"},{"id":"530921207207","name":"文德村委会"},{"id":"530921207208","name":"团山村委会"},{"id":"530921207209","name":"干马村委会"},{"id":"530921207210","name":"罗家寨村委会"},{"id":"530921207211","name":"郭大寨村委会"},{"id":"530922101001","name":"爱华社区"},{"id":"530922101002","name":"草皮街社区"},{"id":"530922101003","name":"新云洲社区"},{"id":"530922101004","name":"毛家村社区"},{"id":"530922101201","name":"永胜村委会"},{"id":"530922101202","name":"德胜村委会"},{"id":"530922101203","name":"河湾村委会"},{"id":"530922101204","name":"平掌村委会"},{"id":"530922101205","name":"水磨村委会"},{"id":"530922101206","name":"勐勐村委会"},{"id":"530922101207","name":"忙回村委会"},{"id":"530922101208","name":"田心村委会"},{"id":"530922101209","name":"河中村委会"},{"id":"530922101210","name":"安河村委会"},{"id":"530922101211","name":"丙山村委会"},{"id":"530922101212","name":"长坡岭村委会"},{"id":"530922101213","name":"夏家箐村委会"},{"id":"530922101214","name":"中良子村委会"},{"id":"530922101215","name":"大树村委会"},{"id":"530922101216","name":"独木村委会"},{"id":"530922101217","name":"河外村委会"},{"id":"530922101218","name":"南河村委会"},{"id":"530922101219","name":"小忙兔村委会"},{"id":"530922101220","name":"头道水村委会"},{"id":"530922101221","name":"石房村委会"},{"id":"530922101222","name":"黑马塘村委会"},{"id":"530922101223","name":"刘家箐村委会"},{"id":"530922101224","name":"垭口田村委会"},{"id":"530922101225","name":"新寨村委会"},{"id":"530922101226","name":"箐口村委会"},{"id":"530922101227","name":"中岭岗村委会"},{"id":"530922101228","name":"大邦卡村委会"},{"id":"530922101229","name":"昔汉村委会"},{"id":"530922102201","name":"漫湾村委会"},{"id":"530922102202","name":"嘎止村委会"},{"id":"530922102203","name":"昔宜村委会"},{"id":"530922102204","name":"草子地村委会"},{"id":"530922102205","name":"密竹林村委会"},{"id":"530922102206","name":"白莺山村委会"},{"id":"530922102207","name":"核桃林村委会"},{"id":"530922102208","name":"酒房村委会"},{"id":"530922102209","name":"水井村委会"},{"id":"530922102210","name":"新村村委会"},{"id":"530922102211","name":"慢光村委会"},{"id":"530922103201","name":"大朝山村委会"},{"id":"530922103202","name":"纸山箐村委会"},{"id":"530922103203","name":"菖蒲塘村委会"},{"id":"530922103204","name":"文物村委会"},{"id":"530922103205","name":"坡头村委会"},{"id":"530922103206","name":"邦旭村委会"},{"id":"530922103207","name":"背阴寨村委会"},{"id":"530922103208","name":"昔元村委会"},{"id":"530922103209","name":"蒿子坝村委会"},{"id":"530922103210","name":"龙潭村委会"},{"id":"530922104201","name":"涌宝村委会"},{"id":"530922104202","name":"邦卡村委会"},{"id":"530922104203","name":"老鲁村委会"},{"id":"530922104204","name":"石头寨村委会"},{"id":"530922104205","name":"分水岭村委会"},{"id":"530922104206","name":"忙亥村委会"},{"id":"530922104207","name":"岔河街村委会"},{"id":"530922104208","name":"浪坝山村委会"},{"id":"530922104209","name":"茶山村委会"},{"id":"530922104210","name":"棠梨树村委会"},{"id":"530922104211","name":"木瓜河村委会"},{"id":"530922104212","name":"石龙村委会"},{"id":"530922104213","name":"胜利村委会"},{"id":"530922104214","name":"荒田村委会"},{"id":"530922104215","name":"龙马塘村委会"},{"id":"530922104216","name":"柄柏村委会"},{"id":"530922104217","name":"糯洒村委会"},{"id":"530922104218","name":"南糯村委会"},{"id":"530922104219","name":"水平村委会"},{"id":"530922104220","name":"南茂河村委会"},{"id":"530922105201","name":"茂兰村委会"},{"id":"530922105202","name":"马四村委会"},{"id":"530922105203","name":"多依村委会"},{"id":"530922105204","name":"忙卓村委会"},{"id":"530922105205","name":"牛圈箐村委会"},{"id":"530922105206","name":"温平村委会"},{"id":"530922105207","name":"净石村委会"},{"id":"530922105208","name":"安乐村委会"},{"id":"530922105209","name":"岭磨村委会"},{"id":"530922105210","name":"拨还河村委会"},{"id":"530922105211","name":"哨街村委会"},{"id":"530922105212","name":"后山村委会"},{"id":"530922105213","name":"丙令村委会"},{"id":"530922105214","name":"旧村村委会"},{"id":"530922105215","name":"转水河村委会"},{"id":"530922106201","name":"海东村委会"},{"id":"530922106202","name":"忙峨村委会"},{"id":"530922106203","name":"控抗村委会"},{"id":"530922106204","name":"邦洪村委会"},{"id":"530922106205","name":"勐底村委会"},{"id":"530922106206","name":"邦信村委会"},{"id":"530922106207","name":"红岗村委会"},{"id":"530922106208","name":"邦别村委会"},{"id":"530922106209","name":"蔑笆山村委会"},{"id":"530922106210","name":"灰窑村委会"},{"id":"530922106211","name":"老鲁山村委会"},{"id":"530922106212","name":"盘村村委会"},{"id":"530922106213","name":"干坡村委会"},{"id":"530922106214","name":"邦挖村委会"},{"id":"530922106215","name":"慢蔗村委会"},{"id":"530922106216","name":"哨山村委会"},{"id":"530922106217","name":"幸福村委会"},{"id":"530922106218","name":"掌龙村委会"},{"id":"530922107201","name":"大寨村委会"},{"id":"530922107202","name":"文丰村委会"},{"id":"530922107203","name":"文朵村委会"},{"id":"530922107204","name":"新合村委会"},{"id":"530922107205","name":"新民村委会"},{"id":"530922107206","name":"新华村委会"},{"id":"530922107207","name":"箐门口村委会"},{"id":"530922107208","name":"慢赖村委会"},{"id":"530922107209","name":"团结村委会"},{"id":"530922107210","name":"棠梨坝村委会"},{"id":"530922107211","name":"官房村委会"},{"id":"530922107212","name":"中山村委会"},{"id":"530922107213","name":"龙塘村委会"},{"id":"530922201201","name":"邦六村委会"},{"id":"530922201202","name":"拉弄村委会"},{"id":"530922201203","name":"慢卡村委会"},{"id":"530922201204","name":"高井槽村委会"},{"id":"530922201205","name":"丙茂村委会"},{"id":"530922201206","name":"麦地村委会"},{"id":"530922201207","name":"新街村委会"},{"id":"530922201208","name":"新路村委会"},{"id":"530922201209","name":"新平村委会"},{"id":"530922201210","name":"温速村委会"},{"id":"530922201211","name":"忙贵村委会"},{"id":"530922202201","name":"晓街村委会"},{"id":"530922202202","name":"老棚村委会"},{"id":"530922202203","name":"大坟村委会"},{"id":"530922202204","name":"老许村委会"},{"id":"530922202205","name":"慢笼村委会"},{"id":"530922202206","name":"麦场村委会"},{"id":"530922202207","name":"松坡村委会"},{"id":"530922202208","name":"四家村委会"},{"id":"530922202209","name":"灯盏村委会"},{"id":"530922202210","name":"八角村委会"},{"id":"530922202211","name":"帮烘村委会"},{"id":"530922202212","name":"崑顶村委会"},{"id":"530922202213","name":"万佑村委会"},{"id":"530922202214","name":"快乐村委会"},{"id":"530922202215","name":"芦稿村委会"},{"id":"530922202216","name":"新联村委会"},{"id":"530922202217","name":"老普村委会"},{"id":"530922202218","name":"团山村委会"},{"id":"530922202219","name":"月牙村委会"},{"id":"530922202220","name":"下村村委会"},{"id":"530922203201","name":"茶房村委会"},{"id":"530922203202","name":"村头村委会"},{"id":"530922203203","name":"文茂村委会"},{"id":"530922203204","name":"黑树林村委会"},{"id":"530922203205","name":"桥街村委会"},{"id":"530922203206","name":"甸头山村委会"},{"id":"530922203207","name":"黄沙河村委会"},{"id":"530922203208","name":"大垭口村委会"},{"id":"530922203209","name":"文乃村委会"},{"id":"530922203210","name":"大河边村委会"},{"id":"530922203211","name":"马街村委会"},{"id":"530922203212","name":"南挖河村委会"},{"id":"530922203213","name":"大路边村委会"},{"id":"530922203214","name":"南满村委会"},{"id":"530922203215","name":"文雅村委会"},{"id":"530922203216","name":"响水村委会"},{"id":"530922204201","name":"栗树村委会"},{"id":"530922204202","name":"大田山村委会"},{"id":"530922204203","name":"忙蚌村委会"},{"id":"530922204204","name":"满富山村委会"},{"id":"530922204205","name":"丙必利村委会"},{"id":"530922204206","name":"把等村委会"},{"id":"530922204207","name":"大村村委会"},{"id":"530922204208","name":"沙坝村委会"},{"id":"530922204209","name":"慢干村委会"},{"id":"530922204210","name":"大平掌村委会"},{"id":"530922204211","name":"养马村委会"},{"id":"530922204212","name":"慢郎村委会"},{"id":"530922204213","name":"小帮赶村委会"},{"id":"530922204214","name":"岩子头村委会"},{"id":"530922204215","name":"崎岖笼村委会"},{"id":"530922204216","name":"白水村委会"},{"id":"530922205201","name":"后箐村委会"},{"id":"530922205202","name":"上台村委会"},{"id":"530922205203","name":"梁子村委会"},{"id":"530922205204","name":"邦东村委会"},{"id":"530922205205","name":"白玉景村委会"},{"id":"530922205206","name":"菠萝村委会"},{"id":"530922205207","name":"勤山村委会"},{"id":"530922205208","name":"玉碗水村委会"},{"id":"530922205209","name":"营盘村委会"},{"id":"530922205210","name":"忙亚村委会"},{"id":"530922205211","name":"忙弄村委会"},{"id":"530922501598","name":"幸福农场虚拟生活区"},{"id":"530922502598","name":"新城农场虚拟生活区"},{"id":"530923101001","name":"德顺社区"},{"id":"530923101002","name":"永安社区"},{"id":"530923101201","name":"忙岗村委会"},{"id":"530923101202","name":"忙见田村委会"},{"id":"530923101203","name":"明朗村委会"},{"id":"530923101204","name":"明信坝村委会"},{"id":"530923101205","name":"牛火塘村委会"},{"id":"530923101206","name":"忙海村委会"},{"id":"530923101207","name":"响水村委会"},{"id":"530923101208","name":"大出水村委会"},{"id":"530923101209","name":"茂梧村委会"},{"id":"530923101210","name":"岩岸山村委会"},{"id":"530923101211","name":"勐汞村委会"},{"id":"530923101212","name":"钻山洞村委会"},{"id":"530923101213","name":"户乃村委会"},{"id":"530923101214","name":"大草坝村委会"},{"id":"530923101215","name":"大坝村委会"},{"id":"530923101216","name":"松林村委会"},{"id":"530923102201","name":"小勐统村委会"},{"id":"530923102202","name":"麻栗树村委会"},{"id":"530923102203","name":"丫口村委会"},{"id":"530923102204","name":"河边村委会"},{"id":"530923102205","name":"半坡村委会"},{"id":"530923102206","name":"木瓜河村委会"},{"id":"530923102207","name":"力柴村委会"},{"id":"530923102208","name":"大丫口村委会"},{"id":"530923102209","name":"酸杷根村委会"},{"id":"530923102210","name":"湾甸村委会"},{"id":"530923102211","name":"忙牛水村委会"},{"id":"530923102212","name":"大路街村委会"},{"id":"530923102213","name":"鸭塘村委会"},{"id":"530923102214","name":"班老村委会"},{"id":"530923102215","name":"玉明珠村委会"},{"id":"530923102216","name":"梅子箐村委会"},{"id":"530923103201","name":"永康村委会"},{"id":"530923103202","name":"送吐村委会"},{"id":"530923103203","name":"端德村委会"},{"id":"530923103204","name":"弯腰村委会"},{"id":"530923103205","name":"朝阳村委会"},{"id":"530923103206","name":"热水塘村委会"},{"id":"530923103207","name":"海转村委会"},{"id":"530923103208","name":"送归村委会"},{"id":"530923103209","name":"忙笼村委会"},{"id":"530923103210","name":"忙况村委会"},{"id":"530923103211","name":"忙南糯村委会"},{"id":"530923103212","name":"中山村委会"},{"id":"530923103213","name":"底卡村委会"},{"id":"530923103214","name":"忙度村委会"},{"id":"530923103215","name":"勐底村委会"},{"id":"530923103216","name":"忙捞村委会"},{"id":"530923103217","name":"鸭塘村委会"},{"id":"530923103218","name":"忙腊村委会"},{"id":"530923203201","name":"勐板村委会"},{"id":"530923203202","name":"两沟水村委会"},{"id":"530923203203","name":"白岩村委会"},{"id":"530923203204","name":"梨树村委会"},{"id":"530923203205","name":"怕掌村委会"},{"id":"530923203206","name":"户丫村委会"},{"id":"530923203207","name":"后山村委会"},{"id":"530923203208","name":"水城村委会"},{"id":"530923203209","name":"忙肺村委会"},{"id":"530923203210","name":"新边田村委会"},{"id":"530923204201","name":"亚练村委会"},{"id":"530923204202","name":"章太村委会"},{"id":"530923204203","name":"文化村委会"},{"id":"530923204204","name":"塔驮村委会"},{"id":"530923204205","name":"兔乃村委会"},{"id":"530923204206","name":"邦木村委会"},{"id":"530923204207","name":"鱼新塘村委会"},{"id":"530923204208","name":"忙回村委会"},{"id":"530923204209","name":"平掌村委会"},{"id":"530923204210","name":"云岭村委会"},{"id":"530923204211","name":"垭口村委会"},{"id":"530923205201","name":"乌木龙村委会"},{"id":"530923205202","name":"新塘村委会"},{"id":"530923205203","name":"木厂村委会"},{"id":"530923205204","name":"小村村委会"},{"id":"530923205205","name":"炭山村委会"},{"id":"530923205206","name":"苍莆塘村委会"},{"id":"530923205207","name":"石灰地村委会"},{"id":"530923205208","name":"扎摸村委会"},{"id":"530923205209","name":"蕨坝村委会"},{"id":"530923205210","name":"帮卖村委会"},{"id":"530923206201","name":"团山村委会"},{"id":"530923206202","name":"勐旨村委会"},{"id":"530923206203","name":"蚂蝗箐村委会"},{"id":"530923206204","name":"曼来村委会"},{"id":"530923206205","name":"大岩房村委会"},{"id":"530923206206","name":"大炉场村委会"},{"id":"530923206207","name":"户婆村委会"},{"id":"530923206208","name":"大平掌村委会"},{"id":"530923207201","name":"班卡村委会"},{"id":"530923207202","name":"忙中村委会"},{"id":"530923207203","name":"忙东村委会"},{"id":"530923207204","name":"松坡村委会"},{"id":"530923207205","name":"尖山村委会"},{"id":"530923207206","name":"放牛场村委会"},{"id":"530923207207","name":"放马场村委会"},{"id":"530923207208","name":"鱼塘村委会"},{"id":"530923208201","name":"崇岗村委会"},{"id":"530923208202","name":"龙竹洼村委会"},{"id":"530923208203","name":"团树村委会"},{"id":"530923208204","name":"龙竹棚村委会"},{"id":"530923208205","name":"军捞村委会"},{"id":"530923208206","name":"蒿子坝村委会"},{"id":"530923208207","name":"忙蚌村委会"},{"id":"530923208208","name":"大落水村委会"},{"id":"530923208209","name":"包山村委会"},{"id":"530923208210","name":"麻力林村委会"},{"id":"530923208211","name":"黑龙村委会"},{"id":"530923209201","name":"大山村委会"},{"id":"530923209202","name":"忙角村委会"},{"id":"530923209203","name":"笼楂村委会"},{"id":"530923209204","name":"纸厂村委会"},{"id":"530923209205","name":"玉华村委会"},{"id":"530923209206","name":"麻栎寨村委会"},{"id":"530923209207","name":"忙兑村委会"},{"id":"530923209208","name":"税房村委会"},{"id":"530923401498","name":"勐底农场虚拟永康分场"},{"id":"530924101001","name":"凤尾镇社区居民委员会"},{"id":"530924101201","name":"凤尾村委会"},{"id":"530924101202","name":"仁和村委会"},{"id":"530924101203","name":"芦子园村委会"},{"id":"530924101204","name":"小水井村委会"},{"id":"530924101205","name":"大柏树村委会"},{"id":"530924101206","name":"大坝村委会"},{"id":"530924102201","name":"勐捧村委会"},{"id":"530924102202","name":"岩子头村委会"},{"id":"530924102203","name":"核桃箐村委会"},{"id":"530924102204","name":"半个山村委会"},{"id":"530924102205","name":"流水村委会"},{"id":"530924102206","name":"象脚水村委会"},{"id":"530924102207","name":"石桥村委会"},{"id":"530924102208","name":"根基村委会"},{"id":"530924102209","name":"丫口村委会"},{"id":"530924102210","name":"忙耿村委会"},{"id":"530924102211","name":"蒿子坝村委会"},{"id":"530924102212","name":"酸格林村委会"},{"id":"530924102213","name":"岔沟村委会"},{"id":"530924102214","name":"南梳坝村委会"},{"id":"530924102215","name":"包包寨村委会"},{"id":"530924102216","name":"忙丙村委会"},{"id":"530924103001","name":"新城社区居民委员会"},{"id":"530924103002","name":"德胜社区居民委员会"},{"id":"530924103201","name":"南伞村委会"},{"id":"530924103202","name":"田坝村委会"},{"id":"530924103203","name":"白岩村委会"},{"id":"530924103204","name":"户育村委会"},{"id":"530924103205","name":"红岩村委会"},{"id":"530924103206","name":"营盘村委会"},{"id":"530924103207","name":"热水河村委会"},{"id":"530924103208","name":"茶山村委会"},{"id":"530924103209","name":"甘塘村委会"},{"id":"530924103210","name":"班龙村委会"},{"id":"530924103211","name":"哈里村委会"},{"id":"530924103212","name":"轩岗村委会"},{"id":"530924103213","name":"麻栗坪村委会"},{"id":"530924103214","name":"道水村委会"},{"id":"530924201201","name":"忙丙村民委员会"},{"id":"530924201202","name":"乌木村委会"},{"id":"530924201203","name":"帮海村民委员会"},{"id":"530924201204","name":"马鞍山村民委员会"},{"id":"530924201205","name":"忙汞村民委员会"},{"id":"530924201206","name":"回掌村民委员会"},{"id":"530924201207","name":"新水村民委员会"},{"id":"530924201208","name":"蔡何村民委员会"},{"id":"530924201209","name":"麦地村民委员会"},{"id":"530924202201","name":"勐堆村委会"},{"id":"530924202202","name":"彭木山村委会"},{"id":"530924202203","name":"铜厂村委会"},{"id":"530924202204","name":"帮东村委会"},{"id":"530924202205","name":"蚌孔村委会"},{"id":"530924202206","name":"竹瓦村委会"},{"id":"530924202207","name":"茶叶林村委会"},{"id":"530924202208","name":"尖山村委会"},{"id":"530924202209","name":"大寨村委会"},{"id":"530924202210","name":"蟒蛇山村委会"},{"id":"530924204201","name":"木场村委会"},{"id":"530924204202","name":"黑马塘村委会"},{"id":"530924204203","name":"绿荫塘村委会"},{"id":"530924204204","name":"散路坝村委会"},{"id":"530924204205","name":"勐撒村委会"},{"id":"530924204206","name":"杨柳桥村委会"},{"id":"530924204207","name":"芹菜塘村委会"},{"id":"530924204208","name":"乌木兰村委会"},{"id":"530924204209","name":"打龙村委会"},{"id":"530924204210","name":"龙塘村委会"},{"id":"530924205201","name":"军赛村委会"},{"id":"530924205202","name":"中厂村委会"},{"id":"530924205203","name":"彩靠村委会"},{"id":"530924205204","name":"南榨村委会"},{"id":"530924205205","name":"岔路村委会"},{"id":"530924205206","name":"忙吉利村委会"},{"id":"530925101001","name":"公很社区"},{"id":"530925101002","name":"新村社区"},{"id":"530925101201","name":"千蚌村委会"},{"id":"530925101202","name":"大荒田村委会"},{"id":"530925101203","name":"闷乐村委会"},{"id":"530925101204","name":"千福村委会"},{"id":"530925101205","name":"忙乐村委会"},{"id":"530925101206","name":"南宋村委会"},{"id":"530925101207","name":"邦迈村委会"},{"id":"530925101208","name":"大吉村委会"},{"id":"530925101209","name":"那布村委会"},{"id":"530925101210","name":"忙建村委会"},{"id":"530925101211","name":"彝家村委会"},{"id":"530925101212","name":"细些村委会"},{"id":"530925101213","name":"红土村委会"},{"id":"530925101214","name":"章外村委会"},{"id":"530925101215","name":"同化村委会"},{"id":"530925102201","name":"城子村委会"},{"id":"530925102202","name":"亥公村委会"},{"id":"530925102203","name":"那赛村委会"},{"id":"530925102204","name":"邦渎村委会"},{"id":"530925102205","name":"那蕉村委会"},{"id":"530925102206","name":"坝糯村委会"},{"id":"530925102207","name":"梁子村委会"},{"id":"530925102208","name":"冰岛村委会"},{"id":"530925102209","name":"坝卡村委会"},{"id":"530925102210","name":"懂过村委会"},{"id":"530925102211","name":"大户赛村委会"},{"id":"530925102212","name":"公弄村委会"},{"id":"530925102213","name":"丙山村委会"},{"id":"530925102214","name":"邦改村委会"},{"id":"530925102215","name":"护东村委会"},{"id":"530925102216","name":"忙那村委会"},{"id":"530925201001","name":"尹甸社区"},{"id":"530925201201","name":"土戈村委会"},{"id":"530925201202","name":"南布村委会"},{"id":"530925201203","name":"允俸村委会"},{"id":"530925201204","name":"忙开村委会"},{"id":"530925201205","name":"邦协村委会"},{"id":"530925201206","name":"邦木村委会"},{"id":"530925201207","name":"陈家村委会"},{"id":"530925201208","name":"平掌村委会"},{"id":"530925201209","name":"营盘村委会"},{"id":"530925201210","name":"下吧哈村委会"},{"id":"530925201211","name":"布京村委会"},{"id":"530925202201","name":"大文村委会"},{"id":"530925202202","name":"大忙蚌村委会"},{"id":"530925202203","name":"大梁子村委会"},{"id":"530925202204","name":"邦驮村委会"},{"id":"530925202205","name":"大南矮村委会"},{"id":"530925202206","name":"忙冒村委会"},{"id":"530925202207","name":"仟信村委会"},{"id":"530925202208","name":"户那村委会"},{"id":"530925202209","name":"太平村委会"},{"id":"530925202210","name":"清平村委会"},{"id":"530925202211","name":"邦烘村委会"},{"id":"530925203201","name":"忙糯村委会"},{"id":"530925203202","name":"小坝子村委会"},{"id":"530925203203","name":"康太村委会"},{"id":"530925203204","name":"邦界村委会"},{"id":"530925203205","name":"荒田村委会"},{"id":"530925203206","name":"巴哈村委会"},{"id":"530925203207","name":"滚岗村委会"},{"id":"530925203208","name":"南骂河村委会"},{"id":"530925203209","name":"富王村委会"},{"id":"530925203210","name":"南亢村委会"},{"id":"530925205201","name":"邦丙村委会"},{"id":"530925205202","name":"南协村委会"},{"id":"530925205203","name":"丫口村委会"},{"id":"530925205204","name":"南栏村委会"},{"id":"530925205205","name":"南直村委会"},{"id":"530925205206","name":"岔箐村委会"},{"id":"530925205207","name":"邦歪村委会"},{"id":"530925205208","name":"邦况村委会"},{"id":"530925205209","name":"忙安村委会"},{"id":"530926100001","name":"甘东社区"},{"id":"530926100002","name":"白马社区"},{"id":"530926100003","name":"白塔社区"},{"id":"530926100200","name":"团结村委会"},{"id":"530926100201","name":"新城村委会"},{"id":"530926100202","name":"芒蚌村委会"},{"id":"530926100203","name":"芒国村委会"},{"id":"530926100204","name":"复兴村委会"},{"id":"530926100205","name":"允楞村委会"},{"id":"530926100206","name":"石灰窑村委会"},{"id":"530926100207","name":"南木弄村委会"},{"id":"530926100208","name":"允捧村委会"},{"id":"530926100209","name":"菜籽地村委会"},{"id":"530926100210","name":"弄巴村委会"},{"id":"530926101004","name":"河底岗社区"},{"id":"530926101200","name":"勐永村委会"},{"id":"530926101201","name":"新和村委会"},{"id":"530926101202","name":"芒来村委会"},{"id":"530926101203","name":"芒佑村委会"},{"id":"530926101204","name":"芒糯村委会"},{"id":"530926101205","name":"帮令村委会"},{"id":"530926101206","name":"香竹林村委会"},{"id":"530926101207","name":"光木林村委会"},{"id":"530926102200","name":"丙令村委会"},{"id":"530926102201","name":"芒茂村委会"},{"id":"530926102202","name":"城子村委会"},{"id":"530926102203","name":"芒枕村委会"},{"id":"530926102204","name":"箐门口村委会"},{"id":"530926102205","name":"班必村委会"},{"id":"530926102206","name":"翁达村委会"},{"id":"530926102207","name":"琅琊村委会"},{"id":"530926102208","name":"户肯村委会"},{"id":"530926103001","name":"城关社区"},{"id":"530926103002","name":"下城社区"},{"id":"530926103202","name":"罕宏村委会"},{"id":"530926103203","name":"贺海村委会"},{"id":"530926103204","name":"遮哈村委会"},{"id":"530926103205","name":"下坝村委会"},{"id":"530926103206","name":"河西村委会"},{"id":"530926103207","name":"新寨村委会"},{"id":"530926103208","name":"景信村委会"},{"id":"530926103209","name":"糯峨村委会"},{"id":"530926103210","name":"芒美村委会"},{"id":"530926103211","name":"邱山村委会"},{"id":"530926103212","name":"德龙村委会"},{"id":"530926103213","name":"芒撒村委会"},{"id":"530926103214","name":"崇岗村委会"},{"id":"530926103215","name":"芒艾村委会"},{"id":"530926103216","name":"色树坝村委会"},{"id":"530926103217","name":"尖坪村委会"},{"id":"530926103218","name":"山头寨村委会"},{"id":"530926103219","name":"班幸村委会"},{"id":"530926103220","name":"清水河村委会"},{"id":"530926103221","name":"尖山村委会"},{"id":"530926103222","name":"大水井村委会"},{"id":"530926200200","name":"大兴村委会"},{"id":"530926200201","name":"岩榴村委会"},{"id":"530926200202","name":"永胜村委会"},{"id":"530926200203","name":"户肯村委会"},{"id":"530926200204","name":"龚家寨村委会"},{"id":"530926200205","name":"班坝村委会"},{"id":"530926201200","name":"芒洪村委会"},{"id":"530926201201","name":"科且村委会"},{"id":"530926201202","name":"安雅村委会"},{"id":"530926201203","name":"新联村委会"},{"id":"530926201204","name":"马厂村委会"},{"id":"530926202200","name":"老寨村委会"},{"id":"530926202201","name":"关弄村委会"},{"id":"530926202202","name":"芒关村委会"},{"id":"530926202203","name":"芒翁村委会"},{"id":"530926202204","name":"梁子寨村委会"},{"id":"530926202205","name":"石佛洞村委会"},{"id":"530926202206","name":"东坡村委会"},{"id":"530926202207","name":"班康村委会"},{"id":"530926203200","name":"贺派村委会"},{"id":"530926203201","name":"芒抗村委会"},{"id":"530926203202","name":"水平村委会"},{"id":"530926203203","name":"落阳村委会"},{"id":"530926203204","name":"崩弄村委会"},{"id":"530926203205","name":"芒底村委会"},{"id":"530926203206","name":"班卖村委会"},{"id":"530926204200","name":"勐简村委会"},{"id":"530926204201","name":"班望村委会"},{"id":"530926204202","name":"迎门寨村委会"},{"id":"530926204203","name":"大寨村委会"},{"id":"530926204204","name":"老厂村委会"},{"id":"530926401598","name":"华侨虚拟生活区"},{"id":"530926402401","name":"洛凌社区"},{"id":"530926402402","name":"分场社区"},{"id":"530926403406","name":"云阳社区"},{"id":"530926403407","name":"姑老河社区"},{"id":"530926403408","name":"小岛社区"},{"id":"530927101001","name":"勐董社区"},{"id":"530927101002","name":"白塔社区"},{"id":"530927101003","name":"永和社区"},{"id":"530927101201","name":"龙乃村委会"},{"id":"530927101202","name":"芒摆村委会"},{"id":"530927101203","name":"永冷村委会"},{"id":"530927101204","name":"怕良村委会"},{"id":"530927101205","name":"坝卡村委会"},{"id":"530927101206","name":"刀董村委会"},{"id":"530927101207","name":"芒回村委会"},{"id":"530927102201","name":"岩帅村委会"},{"id":"530927102202","name":"东勐村委会"},{"id":"530927102203","name":"黄果村委会"},{"id":"530927102204","name":"联合村委会"},{"id":"530927102205","name":"岩丙村委会"},{"id":"530927102206","name":"新华村委会"},{"id":"530927102207","name":"建设村委会"},{"id":"530927102208","name":"贺勐村委会"},{"id":"530927102209","name":"中贺勐村委会"},{"id":"530927102210","name":"贺南村委会"},{"id":"530927102211","name":"新寨村委会"},{"id":"530927102212","name":"团结村委会"},{"id":"530927102213","name":"东米村委会"},{"id":"530927102214","name":"班驮村委会"},{"id":"530927102215","name":"班奈村委会"},{"id":"530927102216","name":"公曼村委会"},{"id":"530927102217","name":"贺科村委会"},{"id":"530927102218","name":"赛弄村委会"},{"id":"530927102219","name":"安海村委会"},{"id":"530927102220","name":"安拐村委会"},{"id":"530927102221","name":"昔勒村委会"},{"id":"530927102222","name":"坝岭村委会"},{"id":"530927103201","name":"勐省村委会"},{"id":"530927103202","name":"回珠村委会"},{"id":"530927103203","name":"满坎村委会"},{"id":"530927103204","name":"芒阳村委会"},{"id":"530927103205","name":"永壤村委会"},{"id":"530927103206","name":"下班奈村委会"},{"id":"530927103207","name":"和平村委会"},{"id":"530927103208","name":"农克村委会"},{"id":"530927104201","name":"芒岗村委会"},{"id":"530927104202","name":"海牙村委会"},{"id":"530927104203","name":"扣勐村委会"},{"id":"530927104204","name":"南腊村委会"},{"id":"530927104205","name":"莱片村委会"},{"id":"530927104206","name":"白岩村委会"},{"id":"530927104207","name":"湖广村委会"},{"id":"530927104208","name":"焦山村委会"},{"id":"530927104209","name":"南景村委会"},{"id":"530927202201","name":"单甲村委会"},{"id":"530927202202","name":"怕结村委会"},{"id":"530927202203","name":"永改村委会"},{"id":"530927202204","name":"安也村委会"},{"id":"530927202205","name":"嘎多村委会"},{"id":"530927202206","name":"永武村委会"},{"id":"530927203201","name":"糯良村委会"},{"id":"530927203202","name":"贺岭村委会"},{"id":"530927203203","name":"南撒村委会"},{"id":"530927203204","name":"怕秋村委会"},{"id":"530927203205","name":"翁不老村委会"},{"id":"530927203206","name":"班考村委会"},{"id":"530927203207","name":"怕迫村委会"},{"id":"530927203208","name":"坝尾村委会"},{"id":"530927204201","name":"民良村委会"},{"id":"530927204202","name":"永安村委会"},{"id":"530927204203","name":"丁来村委会"},{"id":"530927204204","name":"拱弄村委会"},{"id":"530927204205","name":"英格村委会"},{"id":"530927204206","name":"班列村委会"},{"id":"530927204207","name":"勐来村委会"},{"id":"530927204208","name":"公撒村委会"},{"id":"530927204209","name":"曼来村委会"},{"id":"530927205201","name":"勐角村委会"},{"id":"530927205202","name":"莲花塘村委会"},{"id":"530927205203","name":"控角村委会"},{"id":"530927205204","name":"翁丁村委会"},{"id":"530927205205","name":"勐卡村委会"},{"id":"530927205206","name":"芒公村委会"},{"id":"530927205207","name":"糯掌村委会"},{"id":"530927205208","name":"控井村委会"},{"id":"530927205209","name":"勐甘村委会"},{"id":"530927206201","name":"班洪村委会"},{"id":"530927206202","name":"芒库村委会"},{"id":"530927206203","name":"公坎村委会"},{"id":"530927206204","name":"富公村委会"},{"id":"530927206205","name":"班莫村委会"},{"id":"530927206206","name":"南板村委会"},{"id":"530927207201","name":"上班老村委会"},{"id":"530927207202","name":"下班老村委会"},{"id":"530927207203","name":"新寨村委会"},{"id":"530927207204","name":"营盘村委会"},{"id":"530927207205","name":"班搞村委会"},{"id":"530927207206","name":"帕浪村委会"},{"id":"530927401401","name":"机关社区"},{"id":"530927401402","name":"农司社区"},{"id":"530927401403","name":"石佛洞社区"}]